{
  "elements": [
    {
      "element": {
        "element_type": "minecraft:legacy_single_pool_element",
        "location": "more_orn_plants:village/apricot/apricot_tree_0",
        "processors": {
          "processors": []
        },
        "projection": "rigid"
      },
      "weight": 2
    },
    {
      "element": {
        "element_type": "minecraft:legacy_single_pool_element",
        "location": "more_orn_plants:village/apricot/apricot_tree_1",
        "processors": {
          "processors": []
        },
        "projection": "rigid"
      },
      "weight": 2
    },
    {
      "element": {
        "element_type": "minecraft:legacy_single_pool_element",
        "location": "more_orn_plants:village/apricot/apricot_tree_2",
        "processors": {
          "processors": []
        },
        "projection": "rigid"
      },
      "weight": 2
    },
    {
      "element": {
        "element_type": "minecraft:legacy_single_pool_element",
        "location": "more_orn_plants:village/apricot/apricot_tree_3",
        "processors": {
          "processors": []
        },
        "projection": "rigid"
      },
      "weight": 2
    },
    {
      "element": {
        "element_type": "minecraft:empty_pool_element"
      },
      "weight": 1
    }
  ],
  "fallback": "minecraft:empty"
}